loadtest/__init__.py
loadtest-0.0.2.dist-info/LICENSE
loadtest-0.0.2.dist-info/METADATA
loadtest-0.0.2.dist-info/WHEEL
loadtest-0.0.2.dist-info/top_level.txt
loadtest-0.0.2.dist-info/RECORD
