Metadata-Version: 2.1
Name: loadtest
Version: 0.0.2
Summary: Load testing tool
Home-page: https://github.com/geowatson/loadtest
Author: George Watson
Author-email: geowatson@nullteam.info
License: UNKNOWN
Keywords: loadtest
Platform: UNKNOWN
